{
  "run_id": "RUN-026",
  "seed": 1700000026,
  "protocol_name": "BastionConsensus",
  "specification": {
    "name": "BastionConsensus",
    "version": "1.0.0",
    "architecture": "decentralized",
    "node_type": "uniform",
    "quorum_type": "flexible",
    "leader_election": "load_balanced",
    "term_epochs": true,
    "randomized_timeout": true,
    "lease_based": false,
    "voting_model": "weighted_votes",
    "vote_granting": "grant_to_candidate",
    "vote_revocations": true,
    "log_type": "value_log",
    "log_structure": "ring_buffer",
    "commit_method": "batch_commit",
    "recovery_strategy": "hybrid_recovery",
    "snapshot_policy": "periodic",
    "membership_model": "full_dynamic",
    "add_node_method": "consensus_required",
    "remove_node_method": "consensus_required",
    "failure_detection": "adaptive",
    "failure_model": "crash_stop",
    "timeout_model": "proportional",
    "heartbeat_interval": 66,
    "election_timeout_base": 221,
    "election_timeout_range": 151,
    "message_types": [
      "vote_request",
      "vote_response",
      "append_entries",
      "append_response",
      "heartbeat",
      "leader_announce",
      "term_update"
    ],
    "state_machine_type": "fsm",
    "provides_safety": true,
    "provides_liveness": false
  },
  "discovered_features": [
    "leader_election:load_balanced",
    "concept:term_epochs",
    "concept:randomized_timeout",
    "voting:weighted_votes",
    "vote_granting:grant_to_candidate",
    "concept:vote_revocations",
    "log:value_log",
    "log_structure:ring_buffer",
    "commit:batch_commit",
    "recovery:hybrid_recovery",
    "snapshot:periodic",
    "dynamic_membership:full_dynamic",
    "failure_detection:adaptive"
  ],
  "simulations": [
    {
      "protocol_name": "BastionConsensus",
      "num_nodes": 3,
      "measurements": {
        "election_attempts": 41,
        "elections_succeeded": 38,
        "messages_sent": 171,
        "commits": 17,
        "recoveries": 47,
        "partitions": 53,
        "leader_changes": 38,
        "safety_violations": 0,
        "liveness_violations": 0
      },
      "metrics": {
        "election_success_rate": 0.926829268292683,
        "avg_messages_per_commit": 10.058823529411764,
        "leader_stability": 0.0
      },
      "safety_check": true,
      "liveness_check": true
    },
    {
      "protocol_name": "BastionConsensus",
      "num_nodes": 5,
      "measurements": {
        "election_attempts": 55,
        "elections_succeeded": 54,
        "messages_sent": 345,
        "commits": 19,
        "recoveries": 41,
        "partitions": 68,
        "leader_changes": 54,
        "safety_violations": 0,
        "liveness_violations": 0
      },
      "metrics": {
        "election_success_rate": 0.9818181818181818,
        "avg_messages_per_commit": 18.157894736842106,
        "leader_stability": 0.0
      },
      "safety_check": true,
      "liveness_check": true
    },
    {
      "protocol_name": "BastionConsensus",
      "num_nodes": 7,
      "measurements": {
        "election_attempts": 53,
        "elections_succeeded": 52,
        "messages_sent": 423,
        "commits": 26,
        "recoveries": 50,
        "partitions": 53,
        "leader_changes": 52,
        "safety_violations": 0,
        "liveness_violations": 0
      },
      "metrics": {
        "election_success_rate": 0.9811320754716981,
        "avg_messages_per_commit": 16.26923076923077,
        "leader_stability": 0.0
      },
      "safety_check": true,
      "liveness_check": true
    },
    {
      "protocol_name": "BastionConsensus",
      "num_nodes": 9,
      "measurements": {
        "election_attempts": 59,
        "elections_succeeded": 48,
        "messages_sent": 460,
        "commits": 22,
        "recoveries": 47,
        "partitions": 52,
        "leader_changes": 48,
        "safety_violations": 0,
        "liveness_violations": 0
      },
      "metrics": {
        "election_success_rate": 0.8135593220338984,
        "avg_messages_per_commit": 20.90909090909091,
        "leader_stability": 0.0
      },
      "safety_check": true,
      "liveness_check": true
    }
  ],
  "timestamp": "2026-07-20T19:56:46.018055Z"
}